flake8_assert_finder.py
flake8_assert_finder-1.0.dist-info/LICENSE
flake8_assert_finder-1.0.dist-info/METADATA
flake8_assert_finder-1.0.dist-info/WHEEL
flake8_assert_finder-1.0.dist-info/entry_points.txt
flake8_assert_finder-1.0.dist-info/top_level.txt
flake8_assert_finder-1.0.dist-info/RECORD
