Metadata-Version: 2.1
Name: flake8-assert-finder
Version: 1.0
Summary: A simple flake8 Plugin that checks if assert is used
Author-email: JakobDev <jakobdev@gmx.de>
License: BSD-2-Clause
Project-URL: Issues, https://codeberg.org/JakobDev/flake8-assert-finder/issues
Project-URL: Source, https://codeberg.org/JakobDev/flake8-assert-finder
Project-URL: Donation, https://ko-fi.com/jakobdev
Keywords: JakobDev,assert,flake8
Classifier: Development Status :: 5 - Production/Stable
Classifier: Intended Audience :: Developers
Classifier: Environment :: Other Environment
Classifier: License :: OSI Approved :: BSD License
Classifier: Operating System :: OS Independent
Classifier: Operating System :: POSIX
Classifier: Operating System :: POSIX :: BSD
Classifier: Operating System :: POSIX :: Linux
Classifier: Operating System :: MacOS :: MacOS X
Classifier: Operating System :: Microsoft :: Windows
Classifier: Programming Language :: Python :: 3
Classifier: Programming Language :: Python :: 3.9
Classifier: Programming Language :: Python :: 3.10
Classifier: Programming Language :: Python :: 3.11
Classifier: Programming Language :: Python :: 3 :: Only
Classifier: Programming Language :: Python :: Implementation :: CPython
Classifier: Programming Language :: Python :: Implementation :: PyPy
Classifier: Framework :: Flake8
Requires-Python: >=3.9
License-File: LICENSE
Requires-Dist: flake8
